{
  "id": "https://nomadproject.netlify.com/collection/index.json",
  "type": "Collection",
  "items": [
    {
      "id": "https://nomadproject.netlify.com/collection/drinking-vessel/index.json",
      "type": "Manifest",
      "label": {
        "@none": [
          "Drinking Vessel"
        ]
      }
    },
    {
      "id": "https://nomadproject.netlify.com/collection/gold-broach/index.json",
      "type": "Manifest",
      "label": {
        "@none": [
          "Gold Broach"
        ]
      }
    },
    {
      "id": "https://nomadproject.netlify.com/collection/gourd/index.json",
      "type": "Manifest",
      "label": {
        "@none": [
          "Gourd (Ubo)"
        ]
      },
      "thumbnail": [
        {
          "id": "https://nomadproject.netlify.com/collection/gourd/thumb.jpg",
          "type": "Image"
        }
      ]
    },
    {
      "id": "https://nomadproject.netlify.com/collection/headrest/index.json",
      "type": "Manifest",
      "label": {
        "@none": [
          "Headrest (Barkin)"
        ]
      },
      "thumbnail": [
        {
          "id": "https://nomadproject.netlify.com/collection/headrest/thumb.jpg",
          "type": "Image"
        }
      ]
    },
    {
      "id": "https://nomadproject.netlify.com/collection/incense-burner/index.json",
      "type": "Manifest",
      "label": {
        "@none": [
          "Incense Burner (Dabqaad)"
        ]
      },
      "thumbnail": [
        {
          "id": "https://nomadproject.netlify.com/collection/incense-burner/thumb.jpg",
          "type": "Image"
        }
      ]
    },
    {
      "id": "https://nomadproject.netlify.com/collection/milk-vessel/index.json",
      "type": "Manifest",
      "label": {
        "@none": [
          "Milk Vessel (Dhiil)"
        ]
      },
      "thumbnail": [
        {
          "id": "https://nomadproject.netlify.com/collection/milk-vessel/thumb.jpg",
          "type": "Image"
        }
      ]
    },
    {
      "id": "https://nomadproject.netlify.com/collection/serving-vessel/index.json",
      "type": "Manifest",
      "label": {
        "@none": [
          "Serving Vessel"
        ]
      }
    },
    {
      "id": "https://nomadproject.netlify.com/collection/toy-lion/index.json",
      "type": "Manifest",
      "label": {
        "@none": [
          "Toy Lion"
        ]
      },
      "thumbnail": [
        {
          "id": "https://nomadproject.netlify.com/collection/toy-lion/thumb.jpg",
          "type": "Image"
        }
      ]
    },
    {
      "id": "https://nomadproject.netlify.com/collection/wooden-bowl/index.json",
      "type": "Manifest",
      "label": {
        "@none": [
          "Wooden Bowl (Xeero)"
        ]
      },
      "thumbnail": [
        {
          "id": "https://nomadproject.netlify.com/collection/wooden-bowl/thumb.jpg",
          "type": "Image"
        }
      ]
    },
    {
      "id": "https://nomadproject.netlify.com/collection/wooden-comb/index.json",
      "type": "Manifest",
      "label": {
        "@none": [
          "Wooden Comb"
        ]
      }
    },
    {
      "id": "https://nomadproject.netlify.com/collection/wooden-spoon/index.json",
      "type": "Manifest",
      "label": {
        "@none": [
          "Wooden Spoon"
        ]
      }
    },
    {
      "id": "https://nomadproject.netlify.com/collection/woven-basket/index.json",
      "type": "Manifest",
      "label": {
        "@none": [
          "Woven Basket (Masaf)"
        ]
      },
      "thumbnail": [
        {
          "id": "https://nomadproject.netlify.com/collection/woven-basket/thumb.jpg",
          "type": "Image"
        }
      ]
    },
    {
      "id": "https://nomadproject.netlify.com/collection/woven-lid/index.json",
      "type": "Manifest",
      "label": {
        "@none": [
          "Woven Lid"
        ]
      },
      "thumbnail": [
        {
          "id": "https://nomadproject.netlify.com/collection/woven-lid/thumb.jpg",
          "type": "Image"
        }
      ]
    }
  ],
  "label": {
    "@none": [
      "collection"
    ]
  }
}